reflex_qrcode/__init__.py
reflex_qrcode/qrcode.py
reflex_qrcode-0.0.1.dist-info/METADATA
reflex_qrcode-0.0.1.dist-info/WHEEL
reflex_qrcode-0.0.1.dist-info/top_level.txt
reflex_qrcode-0.0.1.dist-info/RECORD
