Metadata-Version: 2.1
Name: reflex-qrcode
Version: 0.0.1
Summary: Reflex custom component QRCode
Author-email: Akshay Ranjan <akshay.ranjan@gmail.com>
License: Apache-2.0
Project-URL: Homepage, https://github.com/onexay/reflex-qrcode
Keywords: reflex,reflex-custom-components
Classifier: Development Status :: 4 - Beta
Requires-Python: >=3.8
Requires-Dist: reflex >=0.4.2
Provides-Extra: dev
Requires-Dist: build ; extra == 'dev'
Requires-Dist: twine ; extra == 'dev'
